gfx_perp_python_sdk/__init__.py
gfx_perp_python_sdk/perp.py
gfx_perp_python_sdk/product.py
gfx_perp_python_sdk/trader.py
gfx_perp_python_sdk-0.0.8.dist-info/LICENSE
gfx_perp_python_sdk-0.0.8.dist-info/METADATA
gfx_perp_python_sdk-0.0.8.dist-info/WHEEL
gfx_perp_python_sdk-0.0.8.dist-info/top_level.txt
gfx_perp_python_sdk-0.0.8.dist-info/RECORD
